AUTHORS
INSTALL
LICENSE
MANIFEST.in
README
README.rst
THANKS
TODO
setup.cfg
setup.py
celery_pylons.egg-info/PKG-INFO
celery_pylons.egg-info/SOURCES.txt
celery_pylons.egg-info/dependency_links.txt
celery_pylons.egg-info/entry_points.txt
celery_pylons.egg-info/requires.txt
celery_pylons.egg-info/top_level.txt
celery_pylons.egg-info/zip-safe
celerypylons/__init__.py
celerypylons/commands.py
celerypylons/loader.py
docs/Makefile
docs/changelog.rst
docs/conf.py
docs/index.rst
docs/introduction.rst
docs/make.bat
docs/getting-started/first-steps-with-pylons.rst
docs/getting-started/index.rst