Metadata-Version: 1.0
Name: celery-pylons
Version: 2.1.4dev
Summary: Celery integration with Pylons.
Home-page: http://pypi.python.org/pypi/celery-pylons
Author: Jonathan Stasiak
Author-email: jonathan.stasiak@gmail.com
License: BSD
Keywords: paste pylons celery message queue amqp job task distributed
Platform: UNKNOWN
Classifier: Development Status :: 4 - Beta
Classifier: Framework :: Pylons
Classifier: Intended Audience :: Developers
Classifier: License :: OSI Approved :: BSD License
Classifier: Operating System :: OS Independent
Classifier: Programming Language :: Python
Classifier: Topic :: Software Development :: Libraries :: Python Modules
Classifier: Topic :: Internet :: WWW/HTTP
Classifier: Topic :: System :: Distributed Computing
